wsgi_sslify
