Metadata-Version: 1.1
Name: wsgi-sslify
Version: 1.0.1
Summary: WSGI middleware to force HTTPS.
Home-page: http://github.com/jacobian/wsgi-sslify
Author: Jacob Kaplan-Moss
Author-email: jacob@jacobian.org
License: UNKNOWN
Platform: UNKNOWN
Classifier: Development Status :: 4 - Beta
Classifier: Environment :: Web Environment
Classifier: Intended Audience :: Developers
Classifier: Intended Audience :: System Administrators
Classifier: License :: OSI Approved :: BSD License
Classifier: Programming Language :: Python :: 2.7
Classifier: Topic :: Internet :: WWW/HTTP :: WSGI :: Middleware
